moh_bob_package1/__init__.py
moh_bob_package1/core.py
moh_bob_package2-0.1.0.dist-info/METADATA
moh_bob_package2-0.1.0.dist-info/WHEEL
moh_bob_package2-0.1.0.dist-info/top_level.txt
moh_bob_package2-0.1.0.dist-info/RECORD
