Metadata-Version: 2.4
Name: moh_bob_package2
Version: 0.1.0
Summary: Un petit package d'exemple
Author-email: Mohamed Boubenia <mohamed@example.com>
License: MIT
Requires-Python: >=3.8
Requires-Dist: requests
